fiscal445/__init__.py
fiscal445/__main__.py
fiscal445/app.py
fiscal445-0.1.6.dist-info/LICENSE
fiscal445-0.1.6.dist-info/METADATA
fiscal445-0.1.6.dist-info/WHEEL
fiscal445-0.1.6.dist-info/top_level.txt
fiscal445-0.1.6.dist-info/RECORD
