Metadata-Version: 2.1
Name: fiscal445
Version: 0.1.6
Summary: 445 Fiscal calendar 
Home-page: https://github.com/dv8edroute/fiscal445/tree/master/fiscal445.0.1.6
Author: Dv8edRoute
Author-email: dv8edroute@protonmail.com
License: MIT
Platform: UNKNOWN
Classifier: Programming Language :: Python :: 3
Classifier: License :: OSI Approved :: MIT License
Classifier: Operating System :: OS Independent
Classifier: Topic :: Office/Business :: Financial :: Accounting
Requires-Python: >=3.6
Requires-Dist: pandas (>=0.25.3)
Requires-Dist: numpy
